[{"category": "2019-01-04", "column-1": "256267"}, {"category": "2019-01-09", "column-1": "193340"}, {"category": "2019-01-14", "column-1": "305184"}, {"category": "2019-01-16", "column-1": "772630"}, {"category": "2019-01-21", "column-1": "230772"}, {"category": "2019-01-23", "column-1": "303478"}, {"category": "2019-01-28", "column-1": "279012"}, {"category": "2019-01-30", "column-1": "420599"}, {"category": "2019-02-01", "column-1": "270606"}, {"category": "2019-02-04", "column-1": "601311"}, {"category": "2019-02-06", "column-1": "182452"}, {"category": "2019-02-11", "column-1": "106126"}, {"category": "2019-02-15", "column-1": "88109"}, {"category": "2019-02-18", "column-1": "98426"}, {"category": "2019-02-20", "column-1": "404771"}, {"category": "2019-02-25", "column-1": "108759"}, {"category": "2019-02-27", "column-1": "246778"}, {"category": "2019-03-11", "column-1": "109104"}, {"category": "2019-03-20", "column-1": "92879"}, {"category": "2019-03-22", "column-1": "110137"}, {"category": "2019-03-25", "column-1": "407053"}, {"category": "2019-03-27", "column-1": "234034"}, {"category": "2019-03-29", "column-1": "128983"}, {"category": "2019-04-01", "column-1": "434294"}, {"category": "2019-04-03", "column-1": "217644"}, {"category": "2019-04-05", "column-1": "544858"}, {"category": "2019-04-08", "column-1": "1190750"}, {"category": "2019-04-10", "column-1": "569150"}, {"category": "2019-04-15", "column-1": "102387"}, {"category": "2019-04-22", "column-1": "684541"}, {"category": "2019-04-24", "column-1": "357261"}, {"category": "2019-04-29", "column-1": "614817"}, {"category": "2019-05-01", "column-1": "846979"}, {"category": "2019-05-06", "column-1": "326083"}, {"category": "2019-05-08", "column-1": "441485"}, {"category": "2019-05-10", "column-1": "146983"}, {"category": "2019-05-13", "column-1": "254052"}, {"category": "2019-05-15", "column-1": "641167"}, {"category": "2019-05-20", "column-1": "661545"}, {"category": "2019-05-21", "column-1": "284001"}, {"category": "2019-05-22", "column-1": "194841"}, {"category": "2019-05-23", "column-1": "264537"}, {"category": "2019-05-29", "column-1": "83251"}, {"category": "2019-05-30", "column-1": "476981"}, {"category": "2019-06-03", "column-1": "271764"}, {"category": "2019-06-05", "column-1": "63878"}, {"category": "2019-06-06", "column-1": "81199"}, {"category": "2019-06-07", "column-1": "138646"}, {"category": "2019-06-08", "column-1": "196163"}, {"category": "2019-06-10", "column-1": "56827"}, {"category": "2019-06-12", "column-1": "85028"}, {"category": "2019-06-13", "column-1": "255224"}, {"category": "2019-06-14", "column-1": "154039"}, {"category": "2019-06-17", "column-1": "154456"}, {"category": "2019-06-18", "column-1": "121197"}, {"category": "2019-06-19", "column-1": "180331"}, {"category": "2019-06-20", "column-1": "61913"}, {"category": "2019-06-21", "column-1": "112284"}, {"category": "2019-06-22", "column-1": "545637"}, {"category": "2019-06-23", "column-1": "63588"}, {"category": "2019-06-24", "column-1": "483221"}, {"category": "2019-06-26", "column-1": "190767"}, {"category": "2019-06-27", "column-1": "669682"}, {"category": "2019-06-28", "column-1": "416767"}, {"category": "2019-06-29", "column-1": "203509"}, {"category": "2019-07-02", "column-1": "177324"}, {"category": "2019-07-03", "column-1": "489581"}, {"category": "2019-07-04", "column-1": "274221"}, {"category": "2019-07-05", "column-1": "161689"}, {"category": "2019-07-06", "column-1": "118721"}, {"category": "2019-07-08", "column-1": "491529"}, {"category": "2019-07-09", "column-1": "124545"}, {"category": "2019-07-10", "column-1": "321567"}, {"category": "2019-07-13", "column-1": "138144"}, {"category": "2019-07-15", "column-1": "270232"}, {"category": "2019-07-16", "column-1": "155987"}, {"category": "2019-07-18", "column-1": "100496"}, {"category": "2019-07-18", "column-1": "23962"}, {"category": "2019-07-19", "column-1": "41956"}, {"category": "2019-07-20", "column-1": "655163"}, {"category": "2019-07-22", "column-1": "269178"}, {"category": "2019-07-23", "column-1": "279557"}, {"category": "2019-07-24", "column-1": "177655"}, {"category": "2019-07-25", "column-1": "193795"}, {"category": "2019-07-26", "column-1": "77915"}, {"category": "2019-07-27", "column-1": "130828"}, {"category": "2019-07-28", "column-1": "67863"}, {"category": "2019-07-30", "column-1": "45935"}, {"category": "2019-07-31", "column-1": "161622"}, {"category": "2019-08-01", "column-1": "176318"}, {"category": "2019-08-02", "column-1": "113193"}, {"category": "2019-08-03", "column-1": "733018"}, {"category": "2019-08-04", "column-1": "701002"}, {"category": "2019-08-05", "column-1": "337143"}, {"category": "2019-08-06", "column-1": "224336"}, {"category": "2019-08-07", "column-1": "209938"}, {"category": "2019-08-08", "column-1": "209889"}, {"category": "2019-08-09", "column-1": "135377"}, {"category": "2019-08-10", "column-1": "174661"}, {"category": "2019-08-11", "column-1": "236972"}, {"category": "2019-08-12", "column-1": "194481"}, {"category": "2019-08-13", "column-1": "95659"}, {"category": "2019-08-14", "column-1": "191535"}, {"category": "2019-08-15", "column-1": "124548"}, {"category": "2019-08-16", "column-1": "100544"}, {"category": "2019-08-17", "column-1": "154651"}, {"category": "2019-08-18", "column-1": "383102"}, {"category": "2019-08-19", "column-1": "157653"}, {"category": "2019-08-21", "column-1": "133472"}, {"category": "2019-08-23", "column-1": "129290"}, {"category": "2019-08-24", "column-1": "511988"}, {"category": "2019-08-26", "column-1": "61874"}, {"category": "2019-08-29", "column-1": "187487"}, {"category": "2019-08-30", "column-1": "54124"}, {"category": "2019-09-02", "column-1": "101064"}, {"category": "2019-09-06", "column-1": "391661"}, {"category": "2019-09-07", "column-1": "134675"}, {"category": "2019-09-09", "column-1": "225491"}, {"category": "2019-09-11", "column-1": "194112"}, {"category": "2019-09-13", "column-1": "122524"}, {"category": "2019-09-16", "column-1": "154984"}, {"category": "2019-09-18", "column-1": "36392"}, {"category": "2019-09-20", "column-1": "149579"}, {"category": "2019-09-23", "column-1": "124830"}, {"category": "2019-09-25", "column-1": "74428"}, {"category": "2019-09-27", "column-1": "185203"}, {"category": "2019-09-30", "column-1": "68425"}]